{"bond_bloomberg": {"Cpn_Freq": {"full_regex": "Cpn Freq[ ]*[\\w\\/]+", "val_regex": "[\\w\\/]+", "transform_val": {"Q": 4, "S/A": 2, "A": 1}}, "ISIN": {"full_regex": "ISIN[ ]*[A-Z0-9]{12}", "val_regex": "[A-Z0-9]{12}", "transform_val": {}}, "Currency": {"full_regex": "Currency[ ]*[A-Z]{3}", "val_regex": "[A-Z]{3}", "transform_val": {}}, "AddNew": {"full_regex": "Country[ ]*[A-Z ]+", "transform_val": {}, "val_regex": "[A-Z]+"}, "Country": {"full_regex": "Country[ ]*[\\w ]+", "transform_val": {}, "val_regex": "[A-Z]+"}}, "mbs_bloomberg": {"Currency": {"full_regex": "Currency[ ]*[A-Z]{3}", "val_regex": "[A-Z]{3}", "transform_val": {}}}, "cfest_bond": {"Master_Sec": {"full_regex": "Master Sec[ ]*[\\w\\/]+", "transform_val": {}, "val_regex": "[\\w\\/]+"}, "Currency": {"full_regex": "Currency[ ]*[A-Z]{3}", "transform_val": {}, "val_regex": "[A-Z]{3}"}}, "unsettle_trade": {"Trade_ID": {"full_regex": "\\d{10}", "val_regex": "\\d{10}", "transform_val": {}}}, "extract_ytd_trades": {"Book_Account": {"full_regex": "[A-Z]{3}\\d{3}", "transform_val": {}, "val_regex": "[A-Z]{3}\\d{3}"}}}